timm/__init__.py
timm/version.py
timm/data/__init__.py
timm/data/auto_augment.py
timm/data/config.py
timm/data/constants.py
timm/data/dataset.py
timm/data/dataset_factory.py
timm/data/distributed_sampler.py
timm/data/loader.py
timm/data/mixup.py
timm/data/random_erasing.py
timm/data/real_labels.py
timm/data/tf_preprocessing.py
timm/data/transforms.py
timm/data/transforms_factory.py
timm/data/parsers/__init__.py
timm/data/parsers/class_map.py
timm/data/parsers/constants.py
timm/data/parsers/parser.py
timm/data/parsers/parser_factory.py
timm/data/parsers/parser_image_folder.py
timm/data/parsers/parser_image_in_tar.py
timm/data/parsers/parser_image_tar.py
timm/data/parsers/parser_tfds.py
timm/loss/__init__.py
timm/loss/asymmetric_loss.py
timm/loss/cross_entropy.py
timm/loss/jsd.py
timm/models/__init__.py
timm/models/byoanet.py
timm/models/byobnet.py
timm/models/cait.py
timm/models/coat.py
timm/models/convit.py
timm/models/cspnet.py
timm/models/densenet.py
timm/models/dla.py
timm/models/dpn.py
timm/models/efficientnet.py
timm/models/efficientnet_blocks.py
timm/models/efficientnet_builder.py
timm/models/factory.py
timm/models/features.py
timm/models/ghostnet.py
timm/models/gluon_resnet.py
timm/models/gluon_xception.py
timm/models/hardcorenas.py
timm/models/helpers.py
timm/models/hrnet.py
timm/models/hub.py
timm/models/inception_resnet_v2.py
timm/models/inception_v3.py
timm/models/inception_v4.py
timm/models/levit.py
timm/models/mlp_mixer.py
timm/models/mobilenetv3.py
timm/models/nasnet.py
timm/models/nfnet.py
timm/models/pit.py
timm/models/pnasnet.py
timm/models/registry.py
timm/models/regnet.py
timm/models/res2net.py
timm/models/resnest.py
timm/models/resnet.py
timm/models/resnetv2.py
timm/models/rexnet.py
timm/models/selecsls.py
timm/models/senet.py
timm/models/sknet.py
timm/models/swin_transformer.py
timm/models/tnt.py
timm/models/tresnet.py
timm/models/twins.py
timm/models/vgg.py
timm/models/visformer.py
timm/models/vision_transformer.py
timm_clean-0.4.12.dist-info/LICENSE
timm_clean-0.4.12.dist-info/METADATA
timm_clean-0.4.12.dist-info/WHEEL
timm_clean-0.4.12.dist-info/top_level.txt
timm_clean-0.4.12.dist-info/RECORD
